src/__init__.py
src/user.py
MarloAPI-0.0.1.dist-info/METADATA
MarloAPI-0.0.1.dist-info/WHEEL
MarloAPI-0.0.1.dist-info/top_level.txt
MarloAPI-0.0.1.dist-info/RECORD
