Metadata-Version: 2.1
Name: MarloAPI
Version: 0.0.1
Summary: A library for working witch Marlo
Author: 2Milan
Author-email: 2Milan <4lish.net@gmail.com>
Classifier: Programming Language :: Python :: 3
Classifier: License :: OSI Approved :: MIT License
Classifier: Operating System :: OS Independent
Requires-Python: >=3.6
Requires-Dist: requests
